chatlet/LICENSE
chatlet/__init__.py
chatlet/debug.py
chatlet/main.py
chatlet/model_pricing.py
chatlet/test_chatlet.py
chatlet/update_model_pricing.py
chatlet-0.1.3.dist-info/METADATA
chatlet-0.1.3.dist-info/WHEEL
chatlet-0.1.3.dist-info/top_level.txt
chatlet-0.1.3.dist-info/RECORD
